dataquality_rules/__init__.py
dataquality_rules/core.py
dataquality_rules-0.1.0.dist-info/LICENSE
dataquality_rules-0.1.0.dist-info/METADATA
dataquality_rules-0.1.0.dist-info/WHEEL
dataquality_rules-0.1.0.dist-info/top_level.txt
dataquality_rules-0.1.0.dist-info/RECORD
